SCET-2.0.111.dist-info/DESCRIPTION.rst
SCET-2.0.111.dist-info/METADATA
SCET-2.0.111.dist-info/RECORD
SCET-2.0.111.dist-info/WHEEL
SCET-2.0.111.dist-info/entry_points.txt
SCET-2.0.111.dist-info/metadata.json
SCET-2.0.111.dist-info/top_level.txt
scet/Contenedores.py
scet/Formularios.py
scet/Mostradores.py
scet/Objetos.py
scet/Plantillas.py
scet/Reportes.py
scet/Selectores.py
scet/Tablas.py
scet/Ventanas.py
scet/__init__.py
scet/bd_xml.py
scet/globales.py
scet/libsa.py
scet/main.py
scet/metadata.cfg
scet/BaseDeDatos/SCET_SQLite.sql
scet/BaseDeDatos/SCET_mysql.sql
scet/InterfacesGraficas/Acerca.ui
scet/InterfacesGraficas/C_Almasenes.ui
scet/InterfacesGraficas/C_Cliente_Nuevo.ui
scet/InterfacesGraficas/C_Clientes.ui
scet/InterfacesGraficas/C_Control_Clientes.ui
scet/InterfacesGraficas/C_Control_Entradas.ui
scet/InterfacesGraficas/C_Control_Recursos.ui
scet/InterfacesGraficas/C_Empresas.ui
scet/InterfacesGraficas/C_Entidades.ui
scet/InterfacesGraficas/C_Entrada_Taller.ui
scet/InterfacesGraficas/C_Herramientas.ui
scet/InterfacesGraficas/C_Historial_Entradas.ui
scet/InterfacesGraficas/C_Objetos.ui
scet/InterfacesGraficas/C_Recurso.ui
scet/InterfacesGraficas/C_Tabla_Busqueda.ui
scet/InterfacesGraficas/C_Tabla_Busqueda_Clientes.ui
scet/InterfacesGraficas/C_Tabla_Busqueda_Entradas.ui
scet/InterfacesGraficas/C_Talleres.ui
scet/InterfacesGraficas/C_Tecnicos.ui
scet/InterfacesGraficas/C_Ubicaciones.ui
scet/InterfacesGraficas/Error.ui
scet/InterfacesGraficas/F_Entidad.ui
scet/InterfacesGraficas/F_Informacion_Fiscal.ui
scet/InterfacesGraficas/F_Objetos.ui
scet/InterfacesGraficas/F_Ubicaciones.ui
scet/InterfacesGraficas/Inicio_seccion.ui
scet/InterfacesGraficas/Main.ui
scet/InterfacesGraficas/P_Contacto.ui
scet/InterfacesGraficas/P_Equipo.ui
scet/InterfacesGraficas/S_Empresas.ui
scet/InterfacesGraficas/T_Almasenes.ui
scet/InterfacesGraficas/T_Caracteristicas.ui
scet/InterfacesGraficas/T_Clientes.ui
scet/InterfacesGraficas/T_Contacto.ui
scet/InterfacesGraficas/T_Descripciones.ui
scet/InterfacesGraficas/T_Empresas.ui
scet/InterfacesGraficas/T_Entradas.ui
scet/InterfacesGraficas/T_EquiposEntrada.ui
scet/InterfacesGraficas/T_Especificaciones.ui
