Metadata-Version: 2.0
Name: SCET
Version: 2.0.111
Summary: Sistema de Control de Entradas de Taller
Home-page: https://bitbucket.org/WolfangT/scet
Author: Wolfang Torres
Author-email: Wolfang.torres@gmail.com
License: MIT
Platform: UNKNOWN
Requires-Dist: pygubu
Requires-Dist: pymysql
Requires-Dist: python-sql
Provides-Extra: PDF
Requires-Dist: lxml; extra == 'PDF'
Requires-Dist: weasyprint; extra == 'PDF'
